{
  "manual" : false,
  "urls" : {
    "-945311047" : {
      "success" : {
        "timestamp" : "2023-09-13T03:17:45.292882733Z"
      }
    },
    "1411079581" : {
      "success" : {
        "timestamp" : "2023-09-13T03:17:53.534589983Z"
      }
    },
    "66423148" : {
      "success" : {
        "timestamp" : "2023-09-13T03:17:54.792646822Z"
      }
    },
    "-1678910968" : {
      "success" : {
        "timestamp" : "2023-09-13T03:17:59.811730238Z"
      }
    },
    "-1733598452" : {
      "success" : {
        "timestamp" : "2023-09-13T03:18:07.328675591Z"
      }
    },
    "-627848280" : {
      "success" : {
        "timestamp" : "2023-09-13T03:18:11.842839527Z"
      }
    }
  }
}