{
  "manual" : false,
  "urls" : {
    "-282345279" : {
      "success" : {
        "timestamp" : "2023-04-28T06:46:40.204683Z"
      }
    },
    "-1447576365" : { },
    "-740945966" : { },
    "1278360492" : { },
    "-1686509370" : { },
    "1741439565" : {
      "error" : {
        "timestamp" : "2023-07-26T03:20:57.399720Z",
        "code" : 404
      }
    },
    "1973080506" : {
      "error" : {
        "timestamp" : "2023-07-26T03:20:57.519412Z",
        "code" : 404
      }
    },
    "1037190494" : {
      "error" : {
        "timestamp" : "2023-07-26T03:20:57.638392Z",
        "code" : 404
      }
    },
    "670514744" : {
      "error" : {
        "timestamp" : "2023-07-26T03:20:57.757472Z",
        "code" : 404
      }
    },
    "155603093" : {
      "error" : {
        "timestamp" : "2023-07-26T03:20:58.081242Z",
        "code" : 404
      }
    },
    "-1633049998" : {
      "error" : {
        "timestamp" : "2023-07-26T03:20:58.275794Z",
        "code" : 404
      }
    },
    "916294566" : {
      "error" : {
        "timestamp" : "2023-07-26T03:20:58.470521Z",
        "code" : 404
      }
    },
    "453644928" : {
      "error" : {
        "timestamp" : "2023-07-26T03:20:58.682927Z",
        "code" : 404
      }
    }
  }
}