{
  "manual" : false,
  "urls" : {
    "1605860143" : {
      "success" : {
        "timestamp" : "2023-06-24T03:39:17.317602Z"
      }
    },
    "-1047053569" : {
      "success" : {
        "timestamp" : "2023-06-24T03:39:25.434388Z"
      }
    },
    "527910504" : {
      "success" : {
        "timestamp" : "2023-06-24T03:39:32.395032Z"
      }
    },
    "-1854017614" : {
      "success" : {
        "timestamp" : "2023-06-24T03:39:38.707970Z"
      }
    },
    "-653605655" : {
      "success" : {
        "timestamp" : "2023-06-24T03:39:43.813412Z"
      }
    }
  }
}