{
  "manual" : false,
  "urls" : {
    "2014435765" : {
      "success" : {
        "timestamp" : "2023-07-26T03:22:00.312204Z"
      }
    },
    "-1266111175" : {
      "success" : {
        "timestamp" : "2023-07-26T03:22:01.487235Z"
      }
    },
    "-1967907986" : {
      "success" : {
        "timestamp" : "2023-07-26T03:22:04.726525Z"
      }
    },
    "197801912" : {
      "success" : {
        "timestamp" : "2023-07-26T03:22:06.780968Z"
      }
    },
    "-1471709789" : {
      "success" : {
        "timestamp" : "2023-07-26T03:22:09.887456Z"
      }
    }
  }
}