{
  "manual" : false,
  "urls" : {
    "-1952668792" : {
      "success" : {
        "timestamp" : "2023-04-28T16:40:07.866214400Z"
      }
    },
    "695666399" : {
      "success" : {
        "timestamp" : "2023-04-28T16:40:08.590785300Z"
      }
    },
    "-1359596986" : {
      "success" : {
        "timestamp" : "2023-04-28T16:40:09.557496700Z"
      }
    },
    "-53931763" : {
      "success" : {
        "timestamp" : "2023-04-28T16:40:10.273178400Z"
      }
    },
    "1852692573" : {
      "success" : {
        "timestamp" : "2023-04-28T16:40:11.019566600Z"
      }
    },
    "1296616470" : {
      "success" : {
        "timestamp" : "2023-04-28T16:40:11.786736200Z"
      }
    }
  }
}